landlab_parallel/__init__.py
landlab_parallel/_version.py
landlab_parallel/adjacency.py
landlab_parallel/ghosts.py
landlab_parallel/grid.py
landlab_parallel/index_mapper.py
landlab_parallel/io.py
landlab_parallel/jagged.py
landlab_parallel/tiler.py
landlab_parallel/utilities.py
landlab_parallel-0.1.0.dist-info/licenses/AUTHORS.md
landlab_parallel-0.1.0.dist-info/licenses/LICENSE.md
landlab_parallel-0.1.0.dist-info/METADATA
landlab_parallel-0.1.0.dist-info/WHEEL
landlab_parallel-0.1.0.dist-info/top_level.txt
landlab_parallel-0.1.0.dist-info/RECORD
