Metadata-Version: 2.4
Name: landlab-parallel
Version: 0.1.0
Summary: Utilities for working with landlab in a parallel environment
Author: Eric Hutton
Author-email: mcflugen@gmail.com
Maintainer: Eric Hutton
Maintainer-email: mcflugen@gmail.com
License: MIT
Project-URL: homepage, https://github.com/mcflugen/landlab-parallel
Project-URL: documentation, https://github.com/mcflugen/landlab-parallel/blob/main/README.md
Project-URL: repository, https://github.com/mcflugen/landlab-parallel
Project-URL: changelog, https://github.com/mcflugen/landlab-parallel/blob/main/CHANGES.md
Keywords: landlab,mpi,parallel,python
Classifier: Development Status :: 4 - Beta
Classifier: Operating System :: OS Independent
Classifier: Topic :: Scientific/Engineering :: Physics
Classifier: License :: OSI Approved :: MIT License
Classifier: Programming Language :: Python :: 3
Classifier: Programming Language :: Python :: 3.11
Classifier: Programming Language :: Python :: 3.12
Classifier: Programming Language :: Python :: 3.13
Classifier: Programming Language :: Python :: 3 :: Only
Classifier: Programming Language :: Python :: Implementation :: CPython
Requires-Python: >=3.11
License-File: LICENSE.md
License-File: AUTHORS.md
Requires-Dist: landlab
Requires-Dist: meshio
Requires-Dist: numpy
Requires-Dist: pymetis
Provides-Extra: dev
Requires-Dist: nox; extra == "dev"
Provides-Extra: testing
Requires-Dist: pytest; extra == "testing"
Dynamic: license-file
